Metadata-Version: 2.1
Name: kame
Version: 0.0.3
Summary: async REST framework
Home-page: https://github.com/ceshm/kame
Author: ceshm
Author-email: cesar.hernandez.mons@gmail.com
License: MIT License
Platform: UNKNOWN
Classifier: Programming Language :: Python :: 3
Classifier: License :: OSI Approved :: MIT License
Classifier: Operating System :: OS Independent
Requires-Python: >=3.6
